[{"X1":177,"X2":5,"D":1},{"X1":2,"X2":50,"D":-1},{"X1":192,"X2":40,"D":1},{"X1":76,"X2":35,"D":1},{"X1":84,"X2":47,"D":1},{"X1":167,"X2":28,"D":1},{"X1":127,"X2":7,"D":1},{"X1":3,"X2":39,"D":-1},{"X1":39,"X2":116,"D":-1},{"X1":195,"X2":155,"D":1},{"X1":183,"X2":110,"D":1},{"X1":107,"X2":101,"D":1},{"X1":150,"X2":170,"D":1},{"X1":1,"X2":124,"D":-1},{"X1":5,"X2":34,"D":-1},{"X1":152,"X2":52,"D":1},{"X1":180,"X2":6,"D":1},{"X1":29,"X2":48,"D":1},{"X1":31,"X2":197,"D":-1},{"X1":184,"X2":194,"D":1}]
